hydrasmac/__init__.py
hydrasmac/hydra/__init__.py
hydrasmac/hydra/hydra.py
hydrasmac/hydra/incumbents.py
hydrasmac/hydra/types.py
hydrasmac/util/__init__.py
hydrasmac/util/scenario_util.py
hydra_smac-0.1.11.dist-info/LICENSE
hydra_smac-0.1.11.dist-info/METADATA
hydra_smac-0.1.11.dist-info/WHEEL
hydra_smac-0.1.11.dist-info/top_level.txt
hydra_smac-0.1.11.dist-info/RECORD
