Metadata-Version: 2.1
Name: hydra-smac
Version: 0.1.11
Summary: Hydra + SMAC
Author: Corné Spek
License: BSD 3-Clause License
Project-URL: Homepage, https://github.com/kw-corne/hydra-smac
Project-URL: Bug Tracker, https://github.com/kw-corne/hydra-smac/issues
Keywords: Hydra,SMAC
Classifier: Operating System :: Unix
Classifier: Programming Language :: Python :: 3.10
Requires-Python: >=3.10
License-File: LICENSE
Requires-Dist: SMAC (==2.0.0)
Provides-Extra: dev
Requires-Dist: black ; extra == 'dev'
Requires-Dist: isort ; extra == 'dev'
Requires-Dist: tox ; extra == 'dev'
Requires-Dist: pytest ; extra == 'dev'
Requires-Dist: pre-commit ; extra == 'dev'
Requires-Dist: flake8 ; extra == 'dev'
Requires-Dist: mypy ; extra == 'dev'
Requires-Dist: bumpver ; extra == 'dev'
Requires-Dist: coverage ; extra == 'dev'
